librecubo_clouds/__init__.py
librecubo_clouds/foo.py
librecubo_clouds-0.0.1.dist-info/LICENSE
librecubo_clouds-0.0.1.dist-info/METADATA
librecubo_clouds-0.0.1.dist-info/WHEEL
librecubo_clouds-0.0.1.dist-info/RECORD
