Metadata-Version: 2.1
Name: librecubo_clouds
Version: 0.0.1
Summary: This is a template repository for Python projects that use Poetry for their dependency management.
Home-page: https://github.com/Julio/librecubo-clouds
Author: Julio Contreras
Author-email: fjulio.contreras1@unmsm.edu.pe
Requires-Python: >=3.9,<4.0
Classifier: Programming Language :: Python :: 3
Classifier: Programming Language :: Python :: 3.9
Classifier: Programming Language :: Python :: 3.10
Classifier: Programming Language :: Python :: 3.11
Classifier: Programming Language :: Python :: 3.12
Requires-Dist: cubo (>=2023.7.2,<2024.0.0)
Project-URL: Documentation, https://Julio.github.io/librecubo-clouds/
Project-URL: Repository, https://github.com/Julio/librecubo-clouds
